springleaf/__init__.py
springleaf/base_generator.py
springleaf/cli.py
springleaf/generator.py
springleaf/springleaf
springleaf/version.py
springleaf/.vscode/settings.json
springleaf/common/project_structures.json
springleaf/common/spring_initializr.json
springleaf/common/version.json
springleaf/common/spring-build/build-gradle.zip
springleaf/common/spring-build/build-maven.zip
springleaf/common/spring-build/build.zip
springleaf/common/templates/Application.java.j2
springleaf/common/templates/ApplicationTests.java.j2
springleaf/common/templates/Controller.java.j2
springleaf/common/templates/Dto.java.j2
springleaf/common/templates/Exception.java.j2
springleaf/common/templates/Mapper.java.j2
springleaf/common/templates/Repository.java.j2
springleaf/common/templates/Request.java.j2
springleaf/common/templates/Service.java.j2
springleaf/common/templates/ServiceImpl.java.j2
springleaf/common/templates/ServletInitializer.java.j2
springleaf/common/templates/build.gradle.j2
springleaf/common/templates/pom.xml.j2
springleaf/utils/__init__.py
springleaf/utils/exceptions.py
springleaf/utils/file_handler.py
springleaf/utils/java_parser.py
springleaf/utils/prompt_builder.py
springleaf/utils/template_util.py
springleaf/utils/handlers/__init__.py
springleaf/utils/handlers/checkbox_handler.py
springleaf/utils/handlers/handler.py
springleaf/utils/handlers/init_handler.py
springleaf/utils/handlers/model_handler.py
springleaf/utils/handlers/name_handler.py
springleaf/utils/handlers/project_structure_handler.py
springleaf/utils/handlers/spring_initializr_handler.py
springleaf-0.4.1.data/scripts/springleaf
springleaf-0.4.1.dist-info/LICENSE
springleaf-0.4.1.dist-info/METADATA
springleaf-0.4.1.dist-info/WHEEL
springleaf-0.4.1.dist-info/top_level.txt
springleaf-0.4.1.dist-info/RECORD
