Metadata-Version: 2.1
Name: springleaf
Version: 0.4.1
Summary: Spring Boot Code Generator
Home-page: https://github.com/OMKE/springleaf
Author: Omar Iriskic
Author-email: contact@omaririskic.com
Maintainer: Omar Iriskic
Maintainer-email: contact@omarirsikic.com
License: UNKNOWN
Download-URL: https://github.com/OMKE/SpringLeaf/archive/0.4.1.tar.gz
Project-URL: Bug Reports, https://github.com/OMKE/SpringLeaf/issues
Project-URL: Source, https://github.com/OMKE/SpringLeaf
Keywords: spring boot cli code generator
Platform: UNKNOWN
Classifier: Programming Language :: Python :: 3
Classifier: License :: OSI Approved :: MIT License
Classifier: Operating System :: OS Independent
Requires-Dist: jinja2
Requires-Dist: javalang
Requires-Dist: questionary
Requires-Dist: pyyaml
Requires-Dist: pyfiglet
Requires-Dist: rich
Requires-Dist: prompt-toolkit (==3.0.2)
